hipe4ml_converter/__init__.py
hipe4ml_converter/h4ml_converter.py
hipe4ml_converter-0.0.7.dist-info/LICENSE
hipe4ml_converter-0.0.7.dist-info/METADATA
hipe4ml_converter-0.0.7.dist-info/WHEEL
hipe4ml_converter-0.0.7.dist-info/entry_points.txt
hipe4ml_converter-0.0.7.dist-info/top_level.txt
hipe4ml_converter-0.0.7.dist-info/RECORD
