Metadata-Version: 2.1
Name: hipe4ml-converter
Version: 0.0.7
Summary: Minimal heavy ion physics environment for Machine Learning
Home-page: https://github.com/hipe4ml/hipe4ml_converter
Author: hipe4ml-developers
Author-email: hipe4ml@googlegroups.com
License: GPL
Classifier: Development Status :: 3 - Alpha
Classifier: Intended Audience :: Education
Classifier: Intended Audience :: Developers
Classifier: Topic :: Scientific/Engineering :: Physics
Classifier: License :: OSI Approved :: GNU General Public License v3 (GPLv3)
Classifier: Programming Language :: Python :: 3.10
Classifier: Programming Language :: Python :: 3.11
Classifier: Programming Language :: Python :: 3.12
Requires-Python: >=3.10
License-File: LICENSE
Requires-Dist: psutil
Requires-Dist: dutil
Requires-Dist: pyarrow>=5.0.0
Requires-Dist: hipe4ml>=0.0.18
Requires-Dist: ipython>=7.16.1
Requires-Dist: jedi==0.17.2
Requires-Dist: torch>=1.7.0
Requires-Dist: scikit-learn>=0.21.3
Requires-Dist: onnxconverter-common>=1.13.0
Requires-Dist: numpy<2.0.0,>=1.23.5
Requires-Dist: skl2onnx>=1.12.0
Requires-Dist: onnxmltools<=1.12.0,>=1.6.0
Requires-Dist: onnxruntime<=1.18.0,>=1.12.0
Requires-Dist: lightgbm>=2.2
Requires-Dist: hummingbird-ml[extra]>=0.4.11
Provides-Extra: dev
Requires-Dist: pylint>=2.6.2; extra == "dev"
Requires-Dist: flake8>=3.8.4; extra == "dev"
Requires-Dist: pytest>=6.2.2; extra == "dev"
Requires-Dist: twine>=3.3.0; extra == "dev"
Requires-Dist: setuptools>=53.0.0; extra == "dev"
Requires-Dist: wheel>=0.36.2; extra == "dev"
